Metadata-Version: 2.1
Name: codegame
Version: 0.0.4
Summary: Python desktop application to create, distribute, discover, and run codegames.
Home-page: https://github.com/pyrustic/codegame
Author: Pyrustic Evangelist
Author-email: rusticalex@yahoo.com
Maintainer: Pyrustic Evangelist
Maintainer-email: rusticalex@yahoo.com
License: MIT
Keywords: serious-game,desktop-app,game,tkinter,teaching,challenge,platform,pyrustic,programming,coding,fun,coding-interview,riddle,puzzle,levels
Platform: UNKNOWN
Classifier: Programming Language :: Python :: 3
Classifier: License :: OSI Approved :: MIT License
Classifier: Operating System :: OS Independent
Requires-Python: >=3.5
License-File: LICENSE
Requires-Dist: tkf
Requires-Dist: shared
Requires-Dist: litemark
Requires-Dist: codeval
